popoto/__init__.py
popoto/exceptions.py
popoto/redis_db.py
popoto/fields/__init__.py
popoto/fields/auto_field_mixin.py
popoto/fields/dataframe_field.py
popoto/fields/datetime_field.py
popoto/fields/field.py
popoto/fields/geo_field.py
popoto/fields/key_field_mixin.py
popoto/fields/relationship.py
popoto/fields/shortcuts.py
popoto/fields/sorted_field_mixin.py
popoto/fields/unique_field_mixin.py
popoto/models/__init__.py
popoto/models/base.py
popoto/models/db_key.py
popoto/models/encoding.py
popoto/models/migrations.py
popoto/models/query.py
popoto/pubsub/__init__.py
popoto/pubsub/publisher.py
popoto/pubsub/subscriber.py
popoto/utils/__init__.py
popoto/utils/list_search.py
popoto/utils/multithreading.py
popoto/utils/sigfigs.py
popoto-0.9.0.dist-info/licenses/LICENSE
popoto-0.9.0.dist-info/METADATA
popoto-0.9.0.dist-info/WHEEL
popoto-0.9.0.dist-info/top_level.txt
popoto-0.9.0.dist-info/RECORD
