Metadata-Version: 2.4
Name: popoto
Version: 0.9.0
Summary: A Python Redis ORM
Home-page: https://github.com/tomcounsell/popoto
Author: Tom Counsell
Author-email: Tom Counsell <other@tomcounsell.com>
License: MIT License
Project-URL: Homepage, https://github.com/tomcounsell/popoto
Project-URL: Documentation, https://popoto.readthedocs.io
Project-URL: Bug_Tracker, https://github.com/tomcounsell/popoto/issues
Keywords: redis,ORM,database
Classifier: License :: OSI Approved :: MIT License
Classifier: Programming Language :: Python
Classifier: Programming Language :: Python :: 3
Classifier: Operating System :: OS Independent
Requires-Python: >=3.8
License-File: LICENSE
Requires-Dist: redis>=4.3.4
Requires-Dist: pandas>=1.4.3
Requires-Dist: numpy>=1.23.1
Requires-Dist: msgpack>=1.0.4
Requires-Dist: msgpack-numpy>=0.4.8
Provides-Extra: dev
Requires-Dist: pytest>=7.1.2; extra == "dev"
Requires-Dist: pytest-asyncio>=0.21.0; extra == "dev"
Requires-Dist: mypy>=0.971; extra == "dev"
Requires-Dist: black>=22.6.0; extra == "dev"
Dynamic: license-file
